server.py
test_mcp_echo_server-0.1.0.dist-info/METADATA
test_mcp_echo_server-0.1.0.dist-info/WHEEL
test_mcp_echo_server-0.1.0.dist-info/entry_points.txt
test_mcp_echo_server-0.1.0.dist-info/top_level.txt
test_mcp_echo_server-0.1.0.dist-info/RECORD
